djangocms_text_ckeditor/__init__.py
djangocms_text_ckeditor/apps.py
djangocms_text_ckeditor/attribute_parsers.py
djangocms_text_ckeditor/cms_plugins.py
djangocms_text_ckeditor/cms_toolbars.py
djangocms_text_ckeditor/fields.py
djangocms_text_ckeditor/forms.py
djangocms_text_ckeditor/html.py
djangocms_text_ckeditor/models.py
djangocms_text_ckeditor/picture_save.py
djangocms_text_ckeditor/sanitizer.py
djangocms_text_ckeditor/settings.py
djangocms_text_ckeditor/utils.py
djangocms_text_ckeditor/widgets.py
djangocms_text_ckeditor/locale/ar/LC_MESSAGES/django.mo
djangocms_text_ckeditor/locale/ar/LC_MESSAGES/django.po
djangocms_text_ckeditor/locale/bn/LC_MESSAGES/django.mo
djangocms_text_ckeditor/locale/bn/LC_MESSAGES/django.po
djangocms_text_ckeditor/locale/ca/LC_MESSAGES/django.mo
djangocms_text_ckeditor/locale/ca/LC_MESSAGES/django.po
djangocms_text_ckeditor/locale/cs/LC_MESSAGES/django.mo
djangocms_text_ckeditor/locale/cs/LC_MESSAGES/django.po
djangocms_text_ckeditor/locale/da/LC_MESSAGES/django.mo
djangocms_text_ckeditor/locale/da/LC_MESSAGES/django.po
djangocms_text_ckeditor/locale/de/LC_MESSAGES/django.mo
djangocms_text_ckeditor/locale/de/LC_MESSAGES/django.po
djangocms_text_ckeditor/locale/el/LC_MESSAGES/django.mo
djangocms_text_ckeditor/locale/el/LC_MESSAGES/django.po
djangocms_text_ckeditor/locale/en/LC_MESSAGES/django.mo
djangocms_text_ckeditor/locale/en/LC_MESSAGES/django.po
djangocms_text_ckeditor/locale/es/LC_MESSAGES/django.mo
djangocms_text_ckeditor/locale/es/LC_MESSAGES/django.po
djangocms_text_ckeditor/locale/et/LC_MESSAGES/django.mo
djangocms_text_ckeditor/locale/et/LC_MESSAGES/django.po
djangocms_text_ckeditor/locale/eu/LC_MESSAGES/django.mo
djangocms_text_ckeditor/locale/eu/LC_MESSAGES/django.po
djangocms_text_ckeditor/locale/fa/LC_MESSAGES/django.mo
djangocms_text_ckeditor/locale/fa/LC_MESSAGES/django.po
djangocms_text_ckeditor/locale/fi/LC_MESSAGES/django.mo
djangocms_text_ckeditor/locale/fi/LC_MESSAGES/django.po
djangocms_text_ckeditor-5.1.7.dist-info/licenses/LICENSE
djangocms_text_ckeditor-5.1.7.dist-info/METADATA
djangocms_text_ckeditor-5.1.7.dist-info/WHEEL
djangocms_text_ckeditor-5.1.7.dist-info/top_level.txt
djangocms_text_ckeditor-5.1.7.dist-info/RECORD
